{
  "updated_at": "2026-07-12T09:00:04.974446+09:00",
  "today": "2026-07-12",
  "github_pages_url": "https://konocturne.github.io/stock",
  "portfolio": {
    "total_cost": 1346862.0,
    "total_eval": 1349600.0,
    "total_pnl": 2738.0,
    "total_pnl_pct": 0.2
  },
  "stocks": [
    {
      "code": "5803",
      "name": "Fujikura Ltd.",
      "quantity": 140,
      "avg_cost": 5164.0,
      "current_price": 5150.0,
      "change_pct_str": "+4.29%",
      "change_str": "+212円",
      "per": "17.0倍",
      "pbr": "15.22倍",
      "div_yield": "74.00%",
      "sector": "Industrials",
      "pnl": -1960.0,
      "pnl_pct": -0.27,
      "eval_total": 721000.0,
      "cost_total": 722960.0,
      "chart_url": "charts/2026-07-12/5803.png",
      "sentiment": "ニュートラル",
      "sentiment_reason": "株価は反発するもテクニカル指標は弱気、高配当利回りに疑問符。",
      "analyst_rating": "買い",
      "consensus_target": 6968,
      "target_divergence_comment": "機関投資家の平均目標株価(6,968円)に対し、現在値(5,150円)は大きく下回っており、約35%の上値余地がある。",
      "stop_loss_guide": 4077,
      "risk_comment": "ベータ値0.778と市場平均より変動が少なく、比較的安定している。しかし、株価は大きく変動しやすい。",
      "technical_detail": "RSIは34.5と中立ながらも売られすぎ水準に接近し、一時的な反発を示唆。MACDはデッドクロス継続で弱気シグナル。株価はBB下限4,077.5円をサポートラインとする動き。",
      "news_impact": "直近で目立ったニュースはなく、特定の材料による株価変動は見られない。",
      "personal_action": "含み損はわずかなため、高配当利回りを考慮しホールドを継続。BB下限4,077.5円を損切りラインとして意識。"
    },
    {
      "code": "285A",
      "name": "KIOXIA HOLDINGS CORPORATION",
      "quantity": 7,
      "avg_cost": 76466.0,
      "current_price": 77000.0,
      "change_pct_str": "-1.10%",
      "change_str": "-860円",
      "per": "76.3倍",
      "pbr": "30.06倍",
      "div_yield": "---",
      "sector": "Technology",
      "pnl": 3738.0,
      "pnl_pct": 0.7,
      "eval_total": 539000.0,
      "cost_total": 535262.0,
      "chart_url": "charts/2026-07-12/285A.png",
      "sentiment": "ポジティブ",
      "sentiment_reason": "株価は下落するも、高成長と機関目標の高さから押し目買いの可能性。",
      "analyst_rating": "買い",
      "consensus_target": 113300,
      "target_divergence_comment": "機関平均目標株価(113,300円)は現在値(77,000円)を大きく上回り、約47%の大きな上値余地がある。",
      "stop_loss_guide": 67339,
      "risk_comment": "ベータ値はデータなし。高成長セクターでボラティリティが高く、短期的な価格変動リスクが大きい。",
      "technical_detail": "RSIは31.0と売られすぎ水準に近く、押し目買いのサイン。MACDはデッドクロス継続で弱気だが、BB下限67,339.4円がサポートとなるか注目。",
      "news_impact": "直近で目立ったニュースはなく、市場全体の半導体動向に影響される傾向。",
      "personal_action": "わずかに含み益。高成長と機関目標を鑑み、BB下限を意識しつつ静観。大幅下落があれば押し目買い検討。"
    },
    {
      "code": "6752",
      "name": "Panasonic Holdings Corporation",
      "quantity": 20,
      "avg_cost": 4432.0,
      "current_price": 4480.0,
      "change_pct_str": "+0.56%",
      "change_str": "+25円",
      "per": "26.5倍",
      "pbr": "2.01倍",
      "div_yield": "121.00%",
      "sector": "Technology",
      "pnl": 960.0,
      "pnl_pct": 1.08,
      "eval_total": 89600.0,
      "cost_total": 88640.0,
      "chart_url": "charts/2026-07-12/6752.png",
      "sentiment": "ニュートラル",
      "sentiment_reason": "株価は小幅高も、機関目標を上回り、テクニカルは弱含み。",
      "analyst_rating": "買い",
      "consensus_target": 4240,
      "target_divergence_comment": "機関平均目標株価(4,240.5円)を現在値(4,480円)が上回っており、目標達成済みまたは上値余地は限定的。",
      "stop_loss_guide": 4048,
      "risk_comment": "ベータ値0.852と市場連動性は高いが、利益成長率がマイナスでありファンダメンタルに懸念点がある。",
      "technical_detail": "RSIは52.4と中立だが、MACDはデッドクロス継続でやや弱気。BB圏内にあり、SMA50を大幅に上回る良好な長期トレンドを示すが、短期的には調整も。",
      "news_impact": "直近で目立ったニュースはなく、特段の株価材料は存在しない。",
      "personal_action": "含み益があるため、機関目標株価を超過している点を考慮し、一部利確を検討。BB下限4,048.5円を損切りラインとする。"
    }
  ],
  "history": [
    {
      "date": "2026-07-12",
      "timing": "夜",
      "ts": "2026-07-12 03:11",
      "alerts": "🚨 KIOXIAのバリュエーション過熱感と全銘柄MACDデッドクロス継続 / 💡 日経225は堅調も、ポートフォリオは個別調整圧力に直面",
      "weather": "半導体:🌤️ / 銀行:☁️",
      "benchmark": "日経225(+1.20%) vs ポートフォリオ: +0.20% (アンダーパフォーム)",
      "strategy": ""
    },
    {
      "date": "2026-07-12",
      "timing": "夜",
      "ts": "2026-07-12 02:49",
      "alerts": "🚨 主要保有銘柄でMACDデッドクロスが継続",
      "weather": "半導体:☁️ / テクノロジー:🌤️ / インダストリアル:☀️",
      "benchmark": "日経225(+1.20%) vs ポートフォリオ: +0.62%",
      "strategy": ""
    },
    {
      "date": "2026-07-12",
      "timing": "夜",
      "ts": "2026-07-12 02:23",
      "alerts": "🚨 5803 MACDデッドクロス継続、短期的な調整警戒。 / 💡 米国市場堅調も、個別株選別は重要。",
      "weather": "半導体:☀️ / 銀行:☁️",
      "benchmark": "日経225(+1.20%) vs ポートフォリオ: -0.27%",
      "strategy": "5803は市場全体の堅調さにも助けられ日中上昇したが、MACDデッドクロスは弱気サイン。含み損益もわずかにマイナス。PTSでの軟調推移を考慮し、一旦利益確定または損切りラインの見直しを検討。中期ではMACDの改善を注視し、買い増しは慎重に。"
    }
  ],
  "ai_report": {
    "title": "朝のアナリスト・レポート",
    "alerts": [
      "🚨 KIOXIAは高い成長性も、バリュエーション過熱感に注意",
      "💡 Fujikuraの異常な高配当利回りはデータエラーの可能性あり、要確認",
      "⚠️ Panasonicは現在値が機関コンセンサス目標を上回っており、上値余地限定的"
    ],
    "weather": "半導体:☁️ / 電機・重電:☀️",
    "benchmark": "日経225(+1.20%) vs ポートフォリオ: +0.20%",
    "market_summary": "昨日の米国市場は主要指数が概ね堅調に推移し、S&P500とNASDAQは小幅高となりました。SOX指数は微増に留まり、半導体セクターの勢いは一服した印象です。日経225は大幅に上昇したものの、本日の日経先物データは取得できませんでした。前日の日本市場の強さを引き継ぎつつも、米国市場の控えめな上昇から、本日はやや利益確定売りに押される場面も想定されます。前夜の予測との比較は、過去の予測データがないため実施できません。",
    "tomorrow_outlook": "米国市場の動向と週末のニュースフローを注視し、半導体関連の指標に注目が集まるでしょう。調整局面があれば押し目買いの好機となる可能性も。",
    "analysis_market": "前日の米国市場は主要指数が堅調に推移したものの、半導体指数(SOX)の伸びは限定的であり、テクノロジーセクターへの過度な期待は一旦落ち着いた模様です。日経225は前日に大幅上昇しており、本日は利益確定の動きも出やすいと予想されます。ただし、円安基調が維持されれば、輸出関連企業には追い風となるでしょう。世界経済の減速懸念が一部で浮上する中、個別銘柄のファンダメンタルズを見極める重要性が増しています。",
    "analysis_technical": "全体的にRSIは中立からやや低めの水準で推移しており、売られすぎ感のある銘柄には反発余地が見られます。MACDは保有銘柄全てでデッドクロスしており、短期的な上値の重さを示すシグナル。しかし、一部銘柄はSMA50を大幅に上回るなど、中期的な上昇トレンドは維持されています。セクターローテーションとしては、過熱感のあった半導体から、出遅れ感のある高配当株や割安株への資金流入が期待される局面かもしれません。",
    "analysis_portfolio": "ポートフォリオ全体ではわずかな含み益を維持しており、全体としては安定しています。テクノロジーセクター（KIOXIA, Panasonic）とインダストリアルセクター（Fujikura）に分散されています。KIOXIAは高成長企業であるものの、高PER・PBRという高バリュエーションであり、リスク管理が重要です。Fujikuraはデータ上の配当利回りが異常な高水準を示しており、この情報の正確性確認が必要です。Panasonicはファンダメンタルズに懸念がありつつも株価は堅調に推移しています。全体的なリスクバランスは良好ですが、個別銘柄のリスク要因に注意が必要です。",
    "strategy_short": "本日の寄り付きでは、日経225の強さから買い意欲が先行する可能性もありますが、前日の米国市場の動きから過度な期待は禁物です。KIOXIAは現在のテクニカル指標と機関目標の乖離から、一時的な下落があれば押し目買いのチャンスと捉える。Panasonicは機関コンセンサス目標を上回っているため、一部利益確定を検討し、次の投資機会に備える。Fujikuraはホールド。",
    "strategy_mid": "今後1〜3ヶ月間は、世界経済の軟着陸期待と各国金融政策の動向が市場を左右する主要因となるでしょう。半導体市況の回復、EV関連需要の推移、企業決算発表が主要な注目イベントです。ポートフォリオとしては、高成長銘柄の押し目買いと、景気回復局面で恩恵を受ける可能性があるディフェンシブ要素も加味したバランス戦略を推奨します。特に、不透明感が強まる場合は、キャッシュポジションの確保も視野に入れるべきです。"
  }
}